win32more/Windows/AI/Actions/__init__.py
win32more/Windows/AI/Actions/Hosting/__init__.py
win32more/Windows/AI/Actions/Provider/__init__.py
win32more/Windows/AI/Agents/__init__.py
win32more/Windows/AI/Agents/Mcp/__init__.py
win32more/Windows/AI/MachineLearning/__init__.py
win32more/Windows/AI/MachineLearning/Preview/__init__.py
win32more/Windows/ApplicationModel/__init__.py
win32more/Windows/ApplicationModel/Activation/__init__.py
win32more/Windows/ApplicationModel/AppExtensions/__init__.py
win32more/Windows/ApplicationModel/AppService/__init__.py
win32more/Windows/ApplicationModel/Appointments/__init__.py
win32more/Windows/ApplicationModel/Appointments/AppointmentsProvider/__init__.py
win32more/Windows/ApplicationModel/Appointments/DataProvider/__init__.py
win32more/Windows/ApplicationModel/Background/__init__.py
win32more/Windows/ApplicationModel/Calls/__init__.py
win32more/Windows/ApplicationModel/Calls/Background/__init__.py
win32more/Windows/ApplicationModel/Calls/Provider/__init__.py
win32more/Windows/ApplicationModel/Chat/__init__.py
win32more/Windows/ApplicationModel/CommunicationBlocking/__init__.py
win32more/Windows/ApplicationModel/Contacts/__init__.py
win32more/Windows/ApplicationModel/Contacts/DataProvider/__init__.py
win32more/Windows/ApplicationModel/Contacts/Provider/__init__.py
win32more/Windows/ApplicationModel/ConversationalAgent/__init__.py
win32more/Windows/ApplicationModel/Core/__init__.py
win32more/Windows/ApplicationModel/DataTransfer/__init__.py
win32more/Windows/ApplicationModel/DataTransfer/DragDrop/__init__.py
win32more/Windows/ApplicationModel/DataTransfer/DragDrop/Core/__init__.py
win32more/Windows/ApplicationModel/DataTransfer/ShareTarget/__init__.py
win32more/Windows/ApplicationModel/Email/__init__.py
win32more/Windows/ApplicationModel/Email/DataProvider/__init__.py
win32more/Windows/ApplicationModel/ExtendedExecution/__init__.py
win32more/Windows/ApplicationModel/ExtendedExecution/Foreground/__init__.py
win32more_microsoft_windows_sdk_contracts-0.8.10.0.26100.7463.dist-info/METADATA
win32more_microsoft_windows_sdk_contracts-0.8.10.0.26100.7463.dist-info/WHEEL
win32more_microsoft_windows_sdk_contracts-0.8.10.0.26100.7463.dist-info/RECORD
