Metadata-Version: 2.4
Name: win32more-Microsoft.Windows.SDK.Contracts
Version: 0.8.10.0.26100.7463
Requires-Dist: win32more-core==0.8.*
